twitter.common.metrics-0.3.11-py2.7-nspkg.pth
twitter/common/metrics/__init__.py
twitter/common/metrics/gauge.py
twitter/common/metrics/metrics.py
twitter/common/metrics/rate.py
twitter/common/metrics/sampler.py
twitter.common.metrics-0.3.11.dist-info/DESCRIPTION.rst
twitter.common.metrics-0.3.11.dist-info/METADATA
twitter.common.metrics-0.3.11.dist-info/RECORD
twitter.common.metrics-0.3.11.dist-info/WHEEL
twitter.common.metrics-0.3.11.dist-info/metadata.json
twitter.common.metrics-0.3.11.dist-info/namespace_packages.txt
twitter.common.metrics-0.3.11.dist-info/top_level.txt
twitter.common.metrics-0.3.11.dist-info/zip-safe
